DeepNN-2020.5.18.11.40.23.dist-info/METADATA
DeepNN-2020.5.18.11.40.23.dist-info/RECORD
DeepNN-2020.5.18.11.40.23.dist-info/WHEEL
DeepNN-2020.5.18.11.40.23.dist-info/entry_points.txt
DeepNN-2020.5.18.11.40.23.dist-info/top_level.txt
Examples/__init__.py
Examples/demo.py
Examples/mcdropout.py
Examples/feature_column/FeatureColumns.py
Examples/feature_column/README.md
Examples/feature_column/__init__.py
Examples/feature_column/demo.py
Tutorials/__init__.py
inn/Require.md
inn/__init__.py
inn/backend.py
inn/demo.py
inn/files.yml
inn/activations/Dice.py
inn/activations/README.md
inn/activations/__init__.py
inn/adversarial_validation/README.md
inn/adversarial_validation/__init__.py
inn/adversarial_validation/shake.py
inn/callbacks/__init__.py
inn/callbacks/wandb_callback.py
inn/config/__init__.py
inn/config/config.yml
inn/config/config_utils.py
inn/cv/KerasCV.py
inn/cv/__init__.py
inn/dateset/Dataset.py
inn/dateset/__init__.py
inn/dateset/tf.record
inn/dateset/tfreader.py
inn/dateset/tfrecord_write.py
inn/dateset/utils.py
inn/deploy/README.md
inn/deploy/__init__.py
inn/deploy/serving/__init__.py
inn/deploy/serving/onnx/__init__.py
inn/deploy/serving/onnx/gbtree.onnx
inn/deploy/serving/onnx/inference.py
inn/deploy/serving/onnx/iris.onnx
inn/deploy/serving/onnx/simplifier_onnx.sh
inn/deploy/serving/onnx/torch_convert.py
inn/deploy/serving/onnx/xgb_convert.py
inn/explainer/README.md
inn/explainer/__init__.py
inn/inputs/__init__.py
inn/inputs/categorical_column.py
inn/inputs/crossed_column.py
inn/inputs/examples.py
inn/inputs/numeric_column.py
inn/inputs/show_column.py
inn/inputs/tf.feature_column.md
inn/inputs/utils.py
inn/layers/Add.py
inn/layers/DNN.py
inn/layers/Linear.py
inn/layers/NoMask.py
inn/layers/Prediction.py
inn/layers/README.md
inn/layers/__init__.py
inn/layers/_layers.py
inn/layers/utils.py
inn/layers/interaction/FM.py
inn/layers/interaction/FM_.py
inn/layers/interaction/__init__.py
inn/layers/normalization/README.md
inn/layers/normalization/__init__.py
inn/learn_rate/__init__.py
inn/learn_rate/clr/CyclicLR.py
inn/learn_rate/clr/__init__.py
inn/losses/__init__.py
inn/metrics/F1Optimizer.py
inn/metrics/__init__.py
