Metadata-Version: 2.1
Name: DeepNN
Version: 2020.5.18.11.40.23
Summary: 深度学习工具类
Home-page: https://github.com/Jie-Yuan/DeepNN
Author: JieYuan
Author-email: 313303303@qq.com
Maintainer: JieYuan
Maintainer-email: 313303303@qq.com
License: MIT
Keywords: deepctr,deepnn,deepfm
Platform: all
Classifier: Operating System :: OS Independent
Classifier: Intended Audience :: Developers
Classifier: License :: OSI Approved :: MIT License
Classifier: Programming Language :: Python
Classifier: Programming Language :: Python :: Implementation
Requires-Python: >=3.6
Requires-Dist: tqdm
Requires-Dist: wrapt
Requires-Dist: loguru
Requires-Dist: sklearn
Requires-Dist: pretty-errors
Requires-Dist: pyforest
Requires-Dist: tensorflow-addons
